pymegafon/__init__.py
pymegafon/__main__.py
pymegafon/balance.py
pymegafon/common.py
pymegafon/credentials.py
pymegafon/megafon.py
pymegafon-1.1.1.dist-info/LICENSE
pymegafon-1.1.1.dist-info/METADATA
pymegafon-1.1.1.dist-info/WHEEL
pymegafon-1.1.1.dist-info/top_level.txt
pymegafon-1.1.1.dist-info/RECORD
