Metadata-Version: 2.1
Name: pymegafon
Version: 1.1.1
Summary: A toolset for interacting with MegaFon account.
Home-page: https://github.com/pymegafon/
Author: Pavel Kim
Author-email: hello@pavelkim.ru
License: UNKNOWN
Platform: UNKNOWN
Classifier: Programming Language :: Python :: 3
Classifier: License :: OSI Approved :: GNU General Public License v3 (GPLv3)
Classifier: Operating System :: OS Independent
Requires-Python: >=3.6
